README.txt
setup.cfg
setup.py
kundart/__init__.py
kundart.socialpublisher.egg-info/PKG-INFO
kundart.socialpublisher.egg-info/SOURCES.txt
kundart.socialpublisher.egg-info/dependency_links.txt
kundart.socialpublisher.egg-info/entry_points.txt
kundart.socialpublisher.egg-info/namespace_packages.txt
kundart.socialpublisher.egg-info/not-zip-safe
kundart.socialpublisher.egg-info/paster_plugins.txt
kundart.socialpublisher.egg-info/requires.txt
kundart.socialpublisher.egg-info/top_level.txt
kundart/socialpublisher/__init__.py
kundart/socialpublisher/bitly.py
kundart/socialpublisher/indexers.py
kundart/socialpublisher/interfaces.py
kundart/socialpublisher/settings.py
kundart/socialpublisher/setuphandlers.py
kundart/socialpublisher/social.py
kundart/socialpublisher/tests.py
kundart/socialpublisher/browser/__init__.py
kundart/socialpublisher/browser/panel.py
kundart/socialpublisher/browser/publish.py
kundart/socialpublisher/viewlets/__init__.py
kundart/socialpublisher/viewlets/viewlet.py