Metadata-Version: 1.0
Name: kundart.socialpublisher
Version: 1.0
Summary: Publish your content to Twitter and Facebook easily
Home-page: http://www.kundart.com
Author: Alvaro Aguirre
Author-email: aaguirre@kundart.com
License: GPL
Keywords: facebook twitter social media
Platform: UNKNOWN
Classifier: Framework :: Plone
Classifier: Programming Language :: Python
